{"which":["sauron","your mom","you","me","your nan","bonus mom","jasmine","clarissa","velma","ravnit","sharleen","talia","harjot","gurpinder","jen","lexie","megan","bonus","parmg","pp","pawanpreet","pawan","eminem","drake","j cole","caroline","sukhjot","george","bilbo","galadriel did it","lebrooon james","the weeknd","mikka","mubdi"],"will":["yep!","no","maybe","of course!","are you an idiot","sure","good question","maybe","of course","naa"],"why":["just because..","because your mom","because you deserve it","same reason my beard is white","because you suck","you are sexy","you got no friends"],"is":["yep!","no","maybe","of course!","are you an idiot","sure","good question","maybe","of course","naa"],"do":["sure","good question","maybe","of course","YES!!","a lot","no","a little","more than anyone","ask again","she likes you","like every other"],"when":["2021","2000","69th full moon after today","tomorrow","yesterday","when you were born","this week","this month","this year","i was there.. 3000 years ago"],"how":["i don't know","don't ask me how","i like you","ask your mother","hmmm.. by sucking","shoot"],"random":["its a nice day","peepa pig","santu claus","You shall not ask!","boring..","whats new","you can ask me anything","oh really"],"what":["your mother","your father","your sister","your boyfriend","motherfather","an idiota"],"would":[],"are":["yep!","no","maybe","of course!","are you an idiot","sure","good question","maybe","of course"],"does":["sure","good question","maybe","of course","YES!!","a lot","no","a little","more than anyone","ask again","she likes you","like every other"],"where":["india","canada","your basement","at her house","in her street","at the park","in your room","on your street","on mars"],"who":["sauron","your mom","you","me","your nan","bonus mom","jasmine","clarissa","velma","ravnit","sharleen","talia","harjot","gurpinder","jen","lexie","megan","bonus","parmg","pp","pawanpreet","pawan","eminem","drake","j cole","caroline","sukhjot","george","bilbo","galadriel did it","lebrooon james","the weeknd","mikka","mubdi"]}